cmdify/__init__.py
cmdify/config.py
cmdify/llm.py
cmdify/main.py
cmdify/sys_utils.py
cmdify-0.3.1.dist-info/METADATA
cmdify-0.3.1.dist-info/WHEEL
cmdify-0.3.1.dist-info/entry_points.txt
cmdify-0.3.1.dist-info/licenses/LICENSE
cmdify-0.3.1.dist-info/RECORD
