Metadata-Version: 2.4
Name: cmdify
Version: 0.3.1
Summary: Cmdify - A tool to translate natural language to shell commands using LLMs
Project-URL: Homepage, https://github.com/jonte/cmdify
Project-URL: Issues, https://github.com/jonte/cmdify/issues
Author-email: Jonte <jonte@example.com>
License: MIT License
License-File: LICENSE
Requires-Python: >=3.9
Requires-Dist: litellm
Requires-Dist: pyperclip
